grizzlys/__init__.py
grizzlys/_utils/__init__.py
grizzlys/_utils/decorators.py
grizzlys/core/__init__.py
grizzlys/core/session.py
grizzlys/dataframe/__init__.py
grizzlys/dataframe/frame.py
grizzlys/interchange/__init__.py
grizzlys/interchange/dataframe.py
grizzlys/io/__init__.py
grizzlys/io/csv/__init__.py
grizzlys/io/csv/reader.py
grizzlys/io/delimited/__init__.py
grizzlys/io/delimited/reader.py
tests/test_common.py
venv/bin/activate_this.py
venv/julia_env/pyjuliapkg/install/share/julia/test/clangsa/lit.cfg.py
venv/julia_env/pyjuliapkg/install/share/julia/test/llvmpasses/lit.cfg.py
grizzlys-0.0.1.dist-info/LICENSE
grizzlys-0.0.1.dist-info/METADATA
grizzlys-0.0.1.dist-info/WHEEL
grizzlys-0.0.1.dist-info/top_level.txt
grizzlys-0.0.1.dist-info/RECORD
