Metadata-Version: 2.1
Name: grizzlys
Version: 0.0.1
Summary: Python DataFrames powered by Julia
Author-email: Hadar Sharon <hadar.sharon94@gmail.com>
License: MIT License
Project-URL: Documentation, https://github.com/hadarsharon/grizzlys/wiki
Project-URL: Repository, https://github.com/hadarsharon/grizzlys
Project-URL: Changelog, https://github.com/hadarsharon/grizzlys/releases
Keywords: python,julia,pandas,polars,koalas,data-science,data-engineering,data-analysis,dataframe,dataframes
Classifier: Development Status :: 1 - Planning
Classifier: Intended Audience :: Developers
Classifier: Intended Audience :: Education
Classifier: Intended Audience :: Information Technology
Classifier: Intended Audience :: Science/Research
Classifier: License :: OSI Approved :: MIT License
Classifier: Operating System :: OS Independent
Classifier: Programming Language :: Python :: 3 :: Only
Classifier: Programming Language :: Python :: 3.10
Classifier: Programming Language :: Python :: 3.11
Classifier: Programming Language :: Python :: 3.12
Classifier: Topic :: Scientific/Engineering
Classifier: Topic :: Scientific/Engineering :: Information Analysis
Classifier: Topic :: Software Development
Classifier: Topic :: Software Development :: Libraries
Classifier: Topic :: Software Development :: Libraries :: Python Modules
Requires-Python: >=3.7
License-File: LICENSE
Requires-Dist: juliacall >=0.9.19
